{
    "message": "hello world",
    "Knowledge base": [
        {
            "animal group": "vertebrate",
            "features": [
                {
                    "name": "backbone",
                    "question": "Does the animal have a backbone or spine?"
                },
                {
                    "name": "skeleton",
                    "question": "Does the animal have an internal skeleton made of bone or cartilage?"
                },
                {
                    "name": "skull",
                    "question": "Does the animal have a head with a brain protected by a skull?"
                }
            ]
        }
    ],
    "Rules": [
        {
            "current animal group": "vertebrate",
            "required feature": [
                "backbone"
            ],
            "question number": 1,
            "next step": "conclusion vertebrate animal"
        },
        {
            "current animal group": "conclusion vertebrate animal",
            "conclusion": "The animal is a vertebrate animal."
        }
    ],
    "Facts": [
        "backbone"
    ]
}
